Metadata-Version: 2.1
Name: kalkulatorxxx
Version: 0.3.0
Summary: Simple Calculator
Home-page: UNKNOWN
Author: Jakub Cichowski
Author-email: kubaxdd1234@wp.pl
License: UNKNOWN
Platform: UNKNOWN
